Workbook

Sheet Leyenda
C2: LEYENDA
C3: GASTOS | D3: CONCEPTOS
C4: Salario | D4: serán los gastos de salario en los que se incurre en el día
C5: Renta | D5: alquiler del espacio se registrará el día que se ejecute el gasto
C6: Compras | D6: compra de mercancias para la venta
C7: Electricidad | D7: monto de la factura pagada
C8: Gas | D8: monto de la factura pagada
C9: Transporte | D9: servicios de transportación de mercancía, mensajeria y servicios de taxi que sean a cuenta del negocio
C10: Pantry | D10: gastos de café, agua, jugos u otros
C11: Comunicaciones | D11: gastos de internet, recargas del móvil asociadas al funcionamiento del negocio, nauta, etc.
C12: Publicidad | D12: gastos asociados a la publicidad y promoción del negocio, modelos, trabajo en redes u otros asociados
C13: Insumos de Limpieza | D13: material e insumos de limpieza asociados al funcionamiento del negocio
C14: Mantenimiento | D14: gastos de mantenimiento y reparacion del local, reposición de luces, pintura, gastos de plomería ect.
... C17: Otros servicios comprados | D17: pagos de otros servicios, por ejemplo: combustible, asesorías, trabajos profesionales

Sheet Ventas
C2: VENTAS
B3: Dia | C3: Turno | D3: TRANSFERENCIAS CUP | E3: TRANSFERENCIAS ZELLE | F3: EURO | G3: USD | H3: EFECTIVO | I3: CUENTA FISCAL | J3: TOTAL | K3: TOTAL USD
B4: 1 | D4: =+'Dia 1'!C4 -> 0 | E4: =+'Dia 1'!D4 -> 0 | F4: =+'Dia 1'!E4 -> 0 | G4: =+'Dia 1'!F4 -> 382 | H4: =+'Dia 1'!G4 -> 0 | I4: =+'Dia 1'!H4 -> 0 | J4: =+'Dia 1'!I4 -> 171900 | K4: =+'Dia 1'!J4 -> 382
B5: 2 | D5: =+'Dia 2'!C4 -> 0 | E5: =+'Dia 2'!D4 -> 0 | F5: =+'Dia 2'!E4 -> 0 | G5: =+'Dia 2'!F4 -> 232 | H5: =+'Dia 2'!G4 -> 38250 | I5: =+'Dia 2'!H4 -> 0 | J5: =+'Dia 2'!I4 -> 142650 | K5: =+'Dia 1'!J5 -> 0
B6: 3 | D6: =+'Dia 3'!C4 -> 0 | E6: =+'Dia 3'!D4 -> 0 | F6: =+'Dia 3'!E4 -> 50 | G6: =+'Dia 3'!F4 -> 174.48 | H6: =+'Dia 3'!G4 -> 0 | I6: =+'Dia 3'!H4 -> 0 | J6: =+'Dia 3'!I4 -> 100516 | K6: =+'Dia 1'!J6 -> 0
B7: 4 | D7: =+'Dia 4'!C4 -> 0 | E7: =+'Dia 4'!D4 -> 0 | F7: =+'Dia 4'!E4 -> 0 | G7: =+'Dia 4'!F4 -> 201 | H7: =+'Dia 4'!G4 -> 7950 | I7: =+'Dia 4'!H4 -> 7800 | J7: =+'Dia 4'!I4 -> 106200 | K7: =+'Dia 1'!J7 -> 0
B8: 5 | D8: =+'Dia 5'!C4 -> 0 | E8: =+'Dia 5'!D4 -> 0 | F8: =+'Dia 5'!E4 -> 0 | G8: =+'Dia 5'!F4 -> 399 | H8: =+'Dia 5'!G4 -> 33250 | I8: =+'Dia 5'!H4 -> 8740 | J8: =+'Dia 5'!I4 -> 221540 | K8: =+'Dia 1'!J8 -> 0
B9: 6 | D9: =+'Dia 6'!C4 -> 22500 | E9: =+'Dia 6'!D4 -> 0 | F9: =+'Dia 6'!E4 -> 0 | G9: =+'Dia 6'!F4 -> 421 | H9: =+'Dia 6'!G4 -> 49800 | I9: =+'Dia 6'!H4 -> 10000 | J9: =+'Dia 6'!I4 -> 271750 | K9: =+'Dia 1'!J9 -> 0
B10: 7 | D10: =+'Dia 7'!C4 -> 0 | E10: =+'Dia 7'!D4 -> 0 | F10: =+'Dia 7'!E4 -> 0 | G10: =+'Dia 7'!F4 -> 134 | H10: =+'Dia 7'!G4 -> 50730 | I10: =+'Dia 7'!H4 -> 0 | J10: =+'Dia 7'!I4 -> 110360 | K10: =+'Dia 1'!J10 -> 0
B11: 8 | D11: =+'Dia 8'!C4 -> 0 | E11: =+'Dia 8'!D4 -> 0 | F11: =+'Dia 8'!E4 -> 0 | G11: =+'Dia 8'!F4 -> 445 | H11: =+'Dia 8'!G4 -> 37505 | I11: =+'Dia 8'!H4 -> 0 | J11: =+'Dia 8'!I4 -> 235530 | K11: =+'Dia 1'!J11 -> 0
B12: 9 | D12: =+'Dia 9'!C4 -> 0 | E12: =+'Dia 9'!D4 -> 0 | F12: =+'Dia 9'!E4 -> 0 | G12: =+'Dia 9'!F4 -> 112 | H12: =+'Dia 9'!G4 -> 37825 | I12: =+'Dia 9'!H4 -> 0 | J12: =+'Dia 9'!I4 -> 87665 | K12: =+'Dia 1'!J12 -> 0
B13: 10 | D13: =+'Dia 10'!C4 -> 0 | E13: =+'Dia 10'!D4 -> 0 | F13: =+'Dia 10'!E4 -> 0 | G13: =+'Dia 10'!F4 -> 275 | H13: =+'Dia 10'!G4 -> 32550 | I13: =+'Dia 10'!H4 -> 0 | J13: =+'Dia 10'!I4 -> 154925 | K13: =+'Dia 1'!J13 -> 0
B14: 11 | D14: =+'Dia 11'!C4 -> 0 | E14: =+'Dia 11'!D4 -> 0 | F14: =+'Dia 11'!E4 -> 0 | G14: =+'Dia 11'!F4 -> 901 | H14: =+'Dia 11'!G4 -> 61275 | I14: =+'Dia 11'!H4 -> 10500 | J14: =+'Dia 11'!I4 -> 477225 | K14: =+'Dia 1'!J14 -> 0
B15: 12 | D15: =+'Dia 12'!C4 -> 6600 | E15: =+'Dia 12'!D4 -> 0 | F15: =+'Dia 12'!E4 -> 0 | G15: =+'Dia 12'!F4 -> 788 | H15: =+'Dia 12'!G4 -> 14950 | I15: =+'Dia 12'!H4 -> 16720 | J15: =+'Dia 12'!I4 -> 384990 | K15: =+'Dia 1'!J15 -> 0
B16: 13 | D16: =+'Dia 13'!C4 -> 0 | E16: =+'Dia 13'!D4 -> 0 | F16: =+'Dia 13'!E4 -> 165 | G16: =+'Dia 13'!F4 -> 957 | H16: =+'Dia 13'!G4 -> 7000 | I16: =+'Dia 13'!H4 -> 0 | J16: =+'Dia 13'!I4 -> 500680 | K16: =+'Dia 1'!J15 -> 0
B17: 14 | D17: =+'Dia 14'!C4 -> 7920 | E17: =+'Dia 14'!D4 -> 0 | F17: =+'Dia 14'!E4 -> 0 | G17: =+'Dia 14'!F4 -> 489 | H17: =+'Dia 14'!G4 -> 17600 | I17: =+'Dia 14'!H4 -> 11000 | J17: =+'Dia 14'!I4 -> 251680 | K17: =+'Dia 1'!J16 -> 0
B18: 15 | D18: =+'Dia 15'!C4 -> 0 | E18: =+'Dia 15'!D4 -> 0 | F18: =+'Dia 15'!E4 -> 0 | G18: =+'Dia 15'!F4 -> 471.4 | H18: =+'Dia 15'!G4 -> 0 | I18: =+'Dia 15'!H4 -> 0 | J18: =+'Dia 15'!I4 -> 207416 | K18: =+'Dia 1'!J17 -> 0
B19: 16 | D19: =+'Dia 16'!C4 -> 0 | E19: =+'Dia 16'!D4 -> 0 | F19: =+'Dia 16'!E4 -> 0 | G19: =+'Dia 16'!F4 -> 504 | H19: =+'Dia 16'!G4 -> 22000 | I19: =+'Dia 16'!H4 -> 0 | J19: =+'Dia 16'!I4 -> 243760 | K19: =+'Dia 1'!J18 -> 0
B20: 17 | D20: =+'Dia 17'!C4 -> 39920 | E20: =+'Dia 17'!D4 -> 0 | F20: =+'Dia 17'!E4 -> 0 | G20: =+'Dia 17'!F4 -> 445 | H20: =+'Dia 17'!G4 -> 154120 | I20: =+'Dia 17'!H4 -> 0 | J20: =+'Dia 17'!I4 -> 389840 | K20: =+'Dia 1'!J19 -> 0
B21: 18 | D21: =+'Dia 18'!C4 -> 0 | E21: =+'Dia 18'!D4 -> 0 | F21: =+'Dia 18'!E4 -> 50 | G21: =+'Dia 18'!F4 -> 224 | H21: =+'Dia 18'!G4 -> 0 | I21: =+'Dia 18'!H4 -> 0 | J21: =+'Dia 18'!I4 -> 116080 | K21: =+'Dia 1'!J20 -> 0
B22: 19 | D22: =+'Dia 19'!C4 -> 0 | E22: =+'Dia 19'!D4 -> 0 | F22: =+'Dia 19'!E4 -> 0 | G22: =+'Dia 19'!F4 -> 0 | H22: =+'Dia 19'!G4 -> 0 | I22: =+'Dia 19'!H4 -> 0 | J22: =+'Dia 19'!I4 -> 0 | K22: =+'Dia 1'!J22 -> 0
B23: 20 | D23: =+'Dia 20'!C4 -> 0 | E23: =+'Dia 20'!D4 -> 0 | F23: =+'Dia 20'!E4 -> 0 | G23: =+'Dia 20'!F4 -> 772 | H23: =+'Dia 20'!G4 -> 30450 | I23: =+'Dia 20'!H4 -> 0 | J23: =+'Dia 20'!I4 -> 370130 | K23: =+'Dia 1'!J23 -> 0
B24: 21 | D24: =+'Dia 21'!C4 -> 0 | E24: =+'Dia 21'!D4 -> 0 | F24: =+'Dia 21'!E4 -> 0 | G24: =+'Dia 21'!F4 -> 412 | H24: =+'Dia 21'!G4 -> 46450 | I24: =+'Dia 21'!H4 -> 0 | J24: =+'Dia 21'!I4 -> 227730 | K24: =+'Dia 1'!J24 -> 0
B25: 22 | D25: =+'Dia 22'!C4 -> 0 | E25: =+'Dia 22'!D4 -> 0 | F25: =+'Dia 22'!E4 -> 0 | G25: =+'Dia 22'!F4 -> 222 | H25: =+'Dia 22'!G4 -> 60940 | I25: =+'Dia 22'!H4 -> 0 | J25: =+'Dia 22'!I4 -> 158620 | K25: =+'Dia 1'!J25 -> 0
B26: 23 | D26: =+'Dia 23'!C4 -> 0 | E26: =+'Dia 23'!D4 -> 0 | F26: =+'Dia 23'!E4 -> 0 | G26: =+'Dia 23'!F4 -> 0 | H26: =+'Dia 23'!G4 -> 0 | I26: =+'Dia 23'!H4 -> 0 | J26: =+'Dia 23'!I4 -> 0 | K26: =+'Dia 1'!J26 -> 0
B27: 24 | D27: =+'Dia 24'!C4 -> 0 | E27: =+'Dia 24'!D4 -> 0 | F27: =+'Dia 24'!E4 -> 0 | G27: =+'Dia 24'!F4 -> 0 | H27: =+'Dia 24'!G4 -> 0 | I27: =+'Dia 24'!H4 -> 0 | J27: =+'Dia 24'!I4 -> 0 | K27: =+'Dia 1'!J27 -> 0
B28: 25 | D28: =+'Dia 25'!C4 -> 0 | E28: =+'Dia 25'!D4 -> 0 | F28: =+'Dia 25'!E4 -> 0 | G28: =+'Dia 25'!F4 -> 0 | H28: =+'Dia 25'!G4 -> 0 | I28: =+'Dia 25'!H4 -> 0 | J28: =+'Dia 25'!I4 -> 0 | K28: =+'Dia 1'!J28 -> 0
B29: 26 | D29: =+'Dia 26'!C4 -> 0 | E29: =+'Dia 26'!D4 -> 0 | F29: =+'Dia 26'!E4 -> 0 | G29: =+'Dia 26'!F4 -> 0 | H29: =+'Dia 26'!G4 -> 0 | I29: =+'Dia 26'!H4 -> 0 | J29: =+'Dia 26'!I4 -> 0 | K29: =+'Dia 1'!J29 -> 0
B30: 27 | D30: =+'Dia 27'!C4 -> 0 | E30: =+'Dia 27'!D4 -> 0 | F30: =+'Dia 27'!E4 -> 0 | G30: =+'Dia 27'!F4 -> 0 | H30: =+'Dia 27'!G4 -> 0 | I30: =+'Dia 27'!H4 -> 0 | J30: =+'Dia 27'!I4 -> 0 | K30: =+'Dia 1'!J30 -> 0
B31: 28 | D31: =+'Dia 28'!C4 -> 0 | E31: =+'Dia 28'!D4 -> 0 | F31: =+'Dia 28'!E4 -> 0 | G31: =+'Dia 28'!F4 -> 0 | H31: =+'Dia 28'!G4 -> 0 | I31: =+'Dia 28'!H4 -> 0 | J31: =+'Dia 28'!I4 -> 0 | K31: =+'Dia 1'!J31 -> 0
B32: 29 | D32: =+'Dia 29'!C4 -> 0 | E32: =+'Dia 29'!D4 -> 0 | F32: =+'Dia 29'!E4 -> 0 | G32: =+'Dia 29'!F4 -> 0 | H32: =+'Dia 29'!G4 -> 0 | I32: =+'Dia 29'!H4 -> 0 | J32: =+'Dia 29'!I4 -> 0 | K32: =+'Dia 1'!J32 -> 0
B33: 30 | D33: =+'Dia 30'!C4 -> 0 | E33: =+'Dia 30'!D4 -> 0 | F33: =+'Dia 30'!E4 -> 0 | G33: =+'Dia 30'!F4 -> 0 | H33: =+'Dia 30'!G4 -> 0 | I33: =+'Dia 30'!H4 -> 0 | J33: =+'Dia 30'!I4 -> 0 | K33: =+'Dia 1'!J35 -> 0
B34: 31 | D34: =+'Dia 31'!C4 -> 0 | E34: =+'Dia 31'!D4 -> 0 | F34: =+'Dia 31'!E4 -> 0 | G34: =+'Dia 31'!F4 -> 0 | H34: =+'Dia 31'!G4 -> 0 | I34: =+'Dia 31'!H4 -> 0 | J34: =+'Dia 31'!I4 -> 0 | K34: =+'Dia 1'!J36 -> 0
B35: TOTAL | D35: =+SUM(D4:D34) -> 76940 | E35: =+SUM(E4:E34) -> 0 | F35: =+SUM(F4:F34) -> 265 | G35: =+SUM(G4:G34) -> 8960.88 | H35: =+SUM(H4:H34) -> 702645 | I35: =+SUM(I4:I34) -> 64760 | J35: =+SUM(J4:J34) -> 4931187 | K35: =+SUM(K4:K34) -> 382
C37: Promedio diario | D37: =+D35/31 -> 2481.9355 | E37: =+E35/31 -> 0 | F37: =+F35/31 -> 8.5483871 | G37: =+G35/31 -> 289.06065 | H37: =+H35/31 -> 22665.968 | I37: =+I35/31 -> 2089.0323 | J37: =+J35/31 -> 159070.55 | K37: =+K35/31 -> 12.322581
D38: TRANSFERENCIAS CUP | E38: TRANSFERENCIAS MLC | F38: EURO | G38: USD | H38: EFECTIVO | I38: CUENTA FISCAL | J38: TOTAL | K38: TOTAL USD

Sheet Salario
C5: Dia1 | D5: Día 2 | E5: Dia3 | F5: Dia4 | G5: Dia5 | H5: Dia6 | I5: Dia7 | J5: Dia8 | K5: Dia9 | L5: Dia10 | M5: Dia11 | N5: Dia12 | O5: Dia13 | P5: Dia14 | Q5: Dia15 | R5: Dia16 | S5: Dia17 | T5: Dia18 | U5: Dia19 | V5: Dia20 | W5: Dia21 | X5: Dia22 | Y5: Dia23 | Z5: Dia24 | AA5: Dia25 | AB5: Dia26 | AC5: Dia27 | AD5: Dia28 | AE5: Dia29 | AF5: Dia30 | AG5: Dia31 | AH5: TOTAL MES
B6: Jacqueline | C6: =+'Dia 1'!C28 -> 2000 | D6: =+'Dia 2'!C28 -> 2000 | E6: =+'Dia 3'!C28 -> 0 | F6: =+'Dia 4'!C28 -> 0 | G6: =+'Dia 5'!C28 -> 0 | H6: =+'Dia 6'!C28 -> 2000 | I6: =+'Dia 7'!C28 -> 0 | J6: =+'Dia 8'!C28 -> 2000 | K6: =+'Dia 9'!C28 -> 0 | L6: =+'Dia 10'!C28 -> 0 | M6: =+'Dia 11'!C28 -> 0 | N6: =+'Dia 12'!C28 -> 2000 | O6: =+'Dia 13'!C28 -> 2000 | P6: =+'Dia 14'!C28 -> 2000 | Q6: =+'Dia 15'!C28 -> 0 | R6: =+'Dia 16'!C28 -> 0 | S6: =+'Dia 17'!C28 -> 0 | T6: =+'Dia 18'!C28 -> 2000 | U6: =+'Dia 19'!C28 -> 0 | V6: =+'Dia 20'!C28 -> 2000 | W6: =+'Dia 21'!C28 -> 0 | X6: =+'Dia 22'!C28 -> 0 | Y6: =+'Dia 23'!C28 -> 0 | Z6: =+'Dia 24'!C28 -> 0 | AA6: =+'Dia 25'!C28 -> 0 | AB6: =+'Dia 26'!C28 -> 0 | AC6: =+'Dia 27'!C28 -> 0 | AD6: =+'Dia 28'!C28 -> 0 | AE6: =+'Dia 29'!C28 -> 0 | AF6: =+'Dia 30'!C28 -> 0 | AG6: =+'Dia 31'!C28 -> 0 | AH6: =SUM(C6:AG6) -> 18000
B7: Yeni | C7: =+'Dia 1'!C29 -> 0 | D7: =+'Dia 2'!C29 -> 0 | E7: =+'Dia 3'!C29 -> 2000 | F7: =+'Dia 4'!C29 -> 0 | G7: =+'Dia 5'!C29 -> 2000 | H7: =+'Dia 6'!C29 -> 0 | I7: =+'Dia 7'!C29 -> 0 | J7: =+'Dia 8'!C29 -> 0 | K7: =+'Dia 9'!C29 -> 2000 | L7: =+'Dia 10'!C29 -> 2000 | M7: =+'Dia 11'!C29 -> 2000 | N7: =+'Dia 12'!C29 -> 0 | O7: =+'Dia 13'!C29 -> 0 | P7: =+'Dia 14'!C29 -> 0 | Q7: =+'Dia 15'!C29 -> 2000 | R7: =+'Dia 16'!C29 -> 2000 | S7: =+'Dia 17'!C29 -> 2000 | T7: =+'Dia 18'!C29 -> 0 | U7: =+'Dia 19'!C29 -> 0 | V7: =+'Dia 20'!C29 -> 0 | W7: =+'Dia 21'!C29 -> 0 | X7: =+'Dia 22'!C29 -> 2000 | Y7: =+'Dia 23'!C29 -> 0 | Z7: =+'Dia 24'!C29 -> 0 | AA7: =+'Dia 25'!C29 -> 0 | AB7: =+'Dia 26'!C29 -> 0 | AC7: =+'Dia 27'!C29 -> 0 | AD7: =+'Dia 28'!C29 -> 0 | AE7: =+'Dia 29'!C29 -> 0 | AF7: =+'Dia 30'!C29 -> 0 | AG7: =+'Dia 31'!C29 -> 0 | AH7: =SUM(C7:AG7) -> 18000
B8: Daniela | C8: =+'Dia 1'!C30 -> 0 | D8: =+'Dia 2'!C30 -> 0 | E8: =+'Dia 3'!C30 -> 0 | F8: =+'Dia 4'!C30 -> 2000 | G8: =+'Dia 5'!C30 -> 0 | H8: =+'Dia 6'!C30 -> 0 | I8: =+'Dia 7'!C30 -> 0 | J8: =+'Dia 8'!C30 -> 0 | K8: =+'Dia 9'!C30 -> 2000 | L8: =+'Dia 10'!C30 -> 0 | M8: =+'Dia 11'!C30 -> 0 | N8: =+'Dia 12'!C30 -> 2000 | O8: =+'Dia 13'!C30 -> 2000 | P8: =+'Dia 14'!C30 -> 2000 | Q8: =+'Dia 15'!C30 -> 0 | R8: =+'Dia 16'!C30 -> 0 | S8: =+'Dia 17'!C30 -> 0 | T8: =+'Dia 18'!C30 -> 0 | U8: =+'Dia 19'!C30 -> 0 | V8: =+'Dia 20'!C30 -> 0 | W8: =+'Dia 21'!C30 -> 0 | X8: =+'Dia 22'!C30 -> 0 | Y8: =+'Dia 23'!C30 -> 0 | Z8: =+'Dia 24'!C30 -> 0 | AA8: =+'Dia 25'!C30 -> 0 | AB8: =+'Dia 26'!C30 -> 0 | AC8: =+'Dia 27'!C30 -> 0 | AD8: =+'Dia 28'!C30 -> 0 | AE8: =+'Dia 29'!C30 -> 0 | AF8: =+'Dia 30'!C30 -> 0 | AG8: =+'Dia 31'!C30 -> 0 | AH8: =SUM(C8:AG8) -> 10000
B9: Mildrey | C9: =+'Dia 1'!C31 -> 0 | D9: =+'Dia 2'!C31 -> 0 | E9: =+'Dia 3'!C31 -> 0 | F9: =+'Dia 4'!C31 -> 2000 | G9: =+'Dia 5'!C31 -> 2000 | H9: =+'Dia 6'!C31 -> 0 | I9: =+'Dia 7'!C31 -> 0 | J9: =+'Dia 8'!C31 -> 0 | K9: =+'Dia 9'!C31 -> 0 | L9: =+'Dia 10'!C31 -> 0 | M9: =+'Dia 11'!C31 -> 0 | N9: =+'Dia 12'!C31 -> 0 | O9: =+'Dia 13'!C31 -> 0 | P9: =+'Dia 14'!C31 -> 0 | Q9: =+'Dia 15'!C31 -> 2000 | R9: =+'Dia 16'!C31 -> 2000 | S9: =+'Dia 17'!C31 -> 2000 | T9: =+'Dia 18'!C31 -> 0 | U9: =+'Dia 19'!C31 -> 0 | V9: =+'Dia 20'!C31 -> 0 | W9: =+'Dia 21'!C31 -> 0 | X9: =+'Dia 22'!C31 -> 2000 | Y9: =+'Dia 23'!C31 -> 0 | Z9: =+'Dia 24'!C31 -> 0 | AA9: =+'Dia 25'!C31 -> 0 | AB9: =+'Dia 26'!C31 -> 0 | AC9: =+'Dia 27'!C31 -> 0 | AD9: =+'Dia 28'!C31 -> 0 | AE9: =+'Dia 29'!C31 -> 0 | AF9: =+'Dia 30'!C31 -> 0 | AG9: =+'Dia 31'!C31 -> 0 | AH9: =SUM(C9:AG9) -> 12000
B10: Aileen | C10: =+'Dia 1'!C32 -> 2000 | D10: =+'Dia 2'!C32 -> 2000 | E10: =+'Dia 3'!C32 -> 0 | F10: =+'Dia 4'!C32 -> 0 | G10: =+'Dia 5'!C32 -> 0 | H10: =+'Dia 6'!C32 -> 2000 | I10: =+'Dia 7'!C32 -> 0 | J10: =+'Dia 8'!C32 -> 2000 | K10: =+'Dia 9'!C32 -> 0 | L10: =+'Dia 10'!C32 -> 2000 | M10: =+'Dia 11'!C32 -> 2000 | N10: =+'Dia 12'!C32 -> 0 | O10: =+'Dia 13'!C32 -> 0 | P10: =+'Dia 14'!C32 -> 0 | Q10: =+'Dia 15'!C32 -> 0 | R10: =+'Dia 16'!C32 -> 0 | S10: =+'Dia 17'!C32 -> 0 | T10: =+'Dia 18'!C32 -> 2000 | U10: =+'Dia 19'!C32 -> 0 | V10: =+'Dia 20'!C32 -> 2000 | W10: =+'Dia 21'!C32 -> 0 | X10: =+'Dia 22'!C32 -> 0 | Y10: =+'Dia 23'!C32 -> 0 | Z10: =+'Dia 24'!C32 -> 0 | AA10: =+'Dia 25'!C32 -> 0 | AB10: =+'Dia 26'!C32 -> 0 | AC10: =+'Dia 27'!C32 -> 0 | AD10: =+'Dia 28'!C32 -> 0 | AE10: =+'Dia 29'!C32 -> 0 | AF10: =+'Dia 30'!C32 -> 0 | AG10: =+'Dia 31'!C32 -> 0 | AH10: =SUM(C10:AG10) -> 16000
B11: Laura | C11: =+'Dia 1'!C33 -> 0 | D11: =+'Dia 1'!D33 -> 0 | E11: =+'Dia 1'!E33 -> 0 | F11: =+'Dia 1'!F33 -> 0 | G11: =+'Dia 1'!G33 -> 0 | H11: =+'Dia 1'!H33 -> 0 | I11: =+'Dia 1'!I33 -> 0 | J11: =+'Dia 1'!J33 -> 0 | ... AG11: =+'Dia 1'!AG33 -> 0 | AH11: =SUM(C11:AG11) -> 0
B12: Vanessa | C12: =+'Dia 1'!C34 -> 0 | D12: =+'Dia 2'!C34 -> 0 | E12: =+'Dia 3'!C34 -> 0 | F12: =+'Dia 4'!C34 -> 0 | G12: =+'Dia 5'!C34 -> 0 | H12: =+'Dia 6'!C34 -> 0 | I12: =+'Dia 7'!C34 -> 0 | J12: =+'Dia 8'!C34 -> 0 | K12: =+'Dia 9'!C34 -> 0 | L12: =+'Dia 10'!C34 -> 0 | M12: =+'Dia 11'!C34 -> 0 | N12: =+'Dia 12'!C34 -> 0 | O12: =+'Dia 13'!C34 -> 0 | P12: =+'Dia 14'!C34 -> 0 | Q12: =+'Dia 15'!C34 -> 0 | R12: =+'Dia 16'!C34 -> 0 | S12: =+'Dia 17'!C34 -> 0 | T12: =+'Dia 18'!C34 -> 0 | U12: =+'Dia 19'!C34 -> 0 | V12: =+'Dia 20'!C34 -> 0 | W12: =+'Dia 21'!C34 -> 0 | X12: =+'Dia 22'!C34 -> 0 | Y12: =+'Dia 23'!C34 -> 0 | Z12: =+'Dia 24'!C34 -> 0 | AA12: =+'Dia 25'!C34 -> 0 | AB12: =+'Dia 26'!C34 -> 0 | AC12: =+'Dia 27'!C34 -> 0 | AD12: =+'Dia 28'!C34 -> 0 | AE12: =+'Dia 29'!C34 -> 0 | AF12: =+'Dia 30'!C34 -> 0 | AG12: =+'Dia 31'!C34 -> 0 | AH12: =SUM(C12:AG12) -> 0
B13: Magaly | C13: =+'Dia 1'!C35 -> 0 | D13: =+'Dia 1'!D35 -> 0 | E13: =+'Dia 1'!E35 -> 0 | F13: =+'Dia 1'!F35 -> 0 | G13: =+'Dia 1'!G35 -> 0 | H13: =+'Dia 1'!H35 -> 0 | I13: =+'Dia 1'!I35 -> 0 | J13: =+'Dia 1'!J35 -> 0 | ... AG13: =+'Dia 1'!AG35 -> 0 | AH13: =SUM(C13:AG13) -> 0
B14: 0.02 | C14: =+'Dia 1'!C37 -> 3438 | D14: =+'Dia 2'!C37 -> 2853 | E14: =+'Dia 3'!E37 -> 0 | F14: =+'Dia 4'!F37 -> 0 | G14: =+'Dia 5'!G37 -> 0 | H14: =+'Dia 6'!H37 -> 0 | I14: =+'Dia 7'!I37 -> 0 | J14: =+'Dia 8'!J37 -> 0 | K14: =+'Dia 9'!K37 -> 0 | L14: =+'Dia 10'!L37 -> 0 | M14: =+'Dia 11'!M37 -> 0 | N14: =+'Dia 12'!N37 -> 0 | O14: =+'Dia 13'!O37 -> 0 | P14: =+'Dia 14'!P37 -> 0 | Q14: =+'Dia 15'!Q37 -> 0 | R14: =+'Dia 1'!R37 -> 0 | S14: =+'Dia 1'!S37 -> 0 | T14: =+'Dia 1'!T37 -> 0 | U14: =+'Dia 1'!U37 -> 0 | V14: =+'Dia 1'!V37 -> 0 | W14: =+'Dia 1'!W37 -> 0 | X14: =+'Dia 1'!X37 -> 0 | Y14: =+'Dia 1'!Y37 -> 0 | ... AG14: =+'Dia 1'!AG37 -> 0 | AH14: =SUM(C14:AG14) -> 6291
C15: =SUM(C6:C14) -> 7438 | D15: =SUM(D6:D14) -> 6853 | E15: =SUM(E6:E14) -> 2000 | F15: =SUM(F6:F14) -> 4000 | G15: =SUM(G6:G14) -> 4000 | H15: =SUM(H6:H14) -> 4000 | I15: =SUM(I6:I14) -> 0 | J15: =SUM(J6:J14) -> 4000 | ... AG15: =SUM(AG6:AG14) -> 0 | AH15: =SUM(C15:AG15) -> 80291
C17: =+'Dia 1'!C41 -> 0 | D17: =+'Dia 2'!C40 -> 0 | E17: =+'Dia 3'!C40 -> 0 | F17: =+'Dia 4'!C40 -> 0 | G17: =+'Dia 5'!C40 -> 0 | H17: =+'Dia 6'!C40 -> 0 | I17: =+'Dia 7'!C40 -> 0 | J17: =+'Dia 8'!C40 -> 0 | K17: =+'Dia 9'!C40 -> 0 | L17: =+'Dia 10'!C40 -> 0 | M17: =+'Dia 11'!C40 -> 0 | N17: =+'Dia 12'!C40 -> 0 | O17: =+'Dia 13'!C40 -> 0 | P17: =+'Dia 14'!C40 -> 0 | Q17: =+'Dia 15'!C40 -> 0 | R17: =+'Dia 16'!C40 -> 0 | S17: =+'Dia 17'!C40 -> 0 | T17: =+'Dia 18'!C40 -> 0 | U17: =+'Dia 19'!C40 -> 0 | V17: =+'Dia 20'!C40 -> 0 | W17: =+'Dia 21'!C40 -> 0 | X17: =+'Dia 22'!C40 -> 0 | Y17: =+'Dia 23'!C40 -> 0 | Z17: =+'Dia 24'!C40 -> 0 | AA17: =+'Dia 25'!C40 -> 0 | AB17: =+'Dia 26'!C40 -> 0 | AC17: =+'Dia 27'!C40 -> 0 | AD17: =+'Dia 28'!C40 -> 0 | AE17: =+'Dia 29'!C40 -> 0 | AF17: =+'Dia 30'!C40 -> 0 | AG17: =+'Dia 31'!C40 -> 0

Sheet Dia 1
B1: Día:1
D2: 450 | E2: 440 | F2: 450
B3: VENTAS | C3: TRANSFERENCIAS CUP | D3: TRANSFERENCIAS ZELLE | E3: EURO | F3: USD | G3: CUP | H3: TRANSFERENCIA A CUENTA FISCAL | I3: TOTAL | J3: TOTAL USD
C4: 0 | D4: 0 | E4: 0 | F4: 382 | G4: 0 | H4: 0 | I4: =+C4+E5+F5+G4+H4+D5 -> 171900 | J4: =+I4/F2 -> 382
D5: =+D4*D2 -> 0 | E5: =+E4*E2 -> 0 | F5: =+F4*F2 -> 171900
B7: Ventas
B8: Ventas Brutas | C8: =+I4 -> 171900
B9: Gastos
B10: SalarioTienda 2% | C10: =+C42 -> 7438
B11: Renta | C11: 0
B12: Compras | C12: 0
B13: Electricidad | C13: 0
B14: Gas | C14: 0
B15: Pantry | C15: 650
B16: Comunicaciones | C16: =D16*F2 -> 67500 | D16: 150
B17: Publicidad | C17: =D17*F2+9000 -> 24750 | D17: 35
B18: Insumos de Limpieza | C18: 0
B19: Mantenimiento | C19: 7000
B20: Insumos para la tienda | C20: 0
B21: Transporte | C21: 0
B22: Servicios contables | C22: 0
B23: Otros servicios comprados | C23: 0
B24: Total de Gastos | C24: =SUM(C10:C23) -> 107338
B27: Salario
B28: Jacqueline | C28: 2000
B29: Yeni
B30: Daniela
B31: Mildrey
B32: Aileen | C32: 2000
B33: Laura
B34: Vanessa
B35: Magaly
B37: 0.02 | C37: =+I4*0.02 -> 3438
B42: Total | C42: =SUM(C28:C41) -> 7438

Sheet Dia 2
B1: Día:2
D2: 440 | E2: 440 | F2: 450
B3: VENTAS | C3: TRANSFERENCIAS CUP | D3: TRANSFERENCIAS ZELLE | E3: EURO | F3: USD | G3: CUP | H3: TRANSFERENCIA A CUENTA FISCAL | I3: TOTAL | J3: TOTAL USD
C4: 0 | D4: 0 | E4: 0 | F4: 232 | G4: 38250 | H4: 0 | I4: =+C4+E5+F5+G4+H4+D5 -> 142650 | J4: =+I4/F2 -> 317
D5: =+D4*D2 -> 0 | E5: =+E4*E2 -> 0 | F5: =+F4*F2 -> 104400
B7: Ventas
B8: Ventas Brutas | C8: =+I4 -> 142650
B9: Gastos
B10: Salario | C10: =+C42 -> 6853
B11: Renta
B12: Compras
B13: Electricidad
B14: Gas
B15: Pantry
B16: Comunicaciones
B17: Publicidad
B18: Insumos de Limpieza
B19: Mantenimiento
B20: Insumos para la tienda
B21: Transporte
B22: Servicios contables
B23: Otros servicios comprados
B24: Total de Gastos | C24: =SUM(C10:C23) -> 6853
B27: Salario
B28: Jacqueline | C28: 2000
B29: Yeni
B30: Daniela
B31: Mildrey
B32: Aileen | C32: 2000
B33: Laura
B34: Vanessa
B35: Magaly
B37: 0.02 | C37: =+I4*0.02 -> 2853
B42: Total | C42: =SUM(C28:C41) -> 6853

Sheet Dia 3
B1: Día:3
D2: 440 | E2: 440 | F2: 450
B3: VENTAS | C3: TRANSFERENCIAS CUP | D3: TRANSFERENCIAS ZELLE | E3: EURO | F3: USD | G3: EFECTIVO | H3: TRANSFERENCIA A CUENTA FISCAL | I3: TOTAL | J3: TOTAL USD
C4: 0 | D4: 0 | E4: 50 | F4: 174.48 | G4: 0 | H4: 0 | I4: =+C4+E5+F5+G4+H4+D5 -> 100516 | J4: =+I4/F2 -> 223.36889
D5: =+D4*D2 -> 0 | E5: =+E4*E2 -> 22000 | F5: =+F4*F2 -> 78516
B7: Ventas
B8: Ventas Brutas | C8: =+I4 -> 100516
B9: Gastos
B10: Salario | C10: =+C42 -> 4010.32
B11: Renta
B12: Compras
B13: Electricidad
B14: Gas
B15: Pantry
B16: Comunicaciones
B17: Publicidad
B18: Insumos de Limpieza
B19: Mantenimiento
B20: Insumos para la tienda
B21: Transporte
B22: Servicios contables
B23: Otros servicios comprados
B24: Total de Gastos | C24: =SUM(C10:C23) -> 4010.32
B27: Salario
B28: Jacqueline
B29: Yeni | C29: 2000
B30: Daniela
B31: Mildrey
B32: Aileen
B33: Laura
B34: Vanessa
B35: Magaly
B37: 0.02 | C37: =+I4*0.02 -> 2010.32
B42: Total | C42: =SUM(C28:C41) -> 4010.32

Sheet Dia 4
B1: Día:4
D2: 440 | E2: 440 | F2: 450
B3: VENTAS | C3: TRANSFERENCIAS CUP | D3: TRANSFERENCIAS ZELLE | E3: EURO | F3: USD | G3: CUP | H3: TRANSFERENCIA A CUENTA FISCAL | I3: TOTAL | J3: TOTAL USD
C4: 0 | D4: 0 | E4: 0 | F4: 201 | G4: 7950 | H4: 7800 | I4: =+C4+E5+F5+G4+H4+D5 -> 106200 | J4: =+I4/F2 -> 236
D5: =+D4*D2 -> 0 | E5: =+E4*E2 -> 0 | F5: =+F4*F2 -> 90450
B7: Ventas
B8: Ventas Brutas | C8: =+I4 -> 106200
B9: Gastos
B10: Salario | C10: =+C42 -> 15124
B11: Renta
B12: Compras
B13: Electricidad
B14: Gas
B15: Pantry
B16: Comunicaciones
B17: Publicidad
B18: Insumos de Limpieza
B19: Mantenimiento
B20: Insumos para la tienda
B21: Transporte
B22: Servicios contables
B23: Otros servicios comprados
B24: Total de Gastos | C24: =SUM(C10:C23) -> 15124
B27: Salario
B28: Jacqueline
B29: Yeni
B30: Daniela | C30: 2000
B31: Mildrey | C31: 2000
B32: Aileen
B33: Laura | C33: =D33*F2 -> 9000 | D33: 20
B34: Vanessa
B35: Magaly
B37: 0.02 | C37: =+I4*0.02 -> 2124
B42: Total | C42: =SUM(C28:C41) -> 15124

Sheet Dia 5
B1: Día: 5
D2: 440 | E2: 440 | F2: 450
B3: VENTAS | C3: TRANSFERENCIAS CUP | D3: TRANSFERENCIAS ZELLE | E3: EURO | F3: USD | G3: CUP | H3: TRANSFERENCIA A CUENTA FISCAL | I3: TOTAL | J3: TOTAL USD
C4: 0 | D4: 0 | E4: 0 | F4: 399 | G4: 33250 | H4: 8740 | I4: =+C4+E5+F5+G4+H4+D5 -> 221540 | J4: =+I4/F2 -> 492.31111
D5: =+D4*D2 -> 0 | E5: =+E4*E2 -> 0 | F5: =+F4*F2 -> 179550
B7: Ventas
B8: Ventas Brutas | C8: =+I4 -> 221540
B9: Gastos
B10: Salario | C10: =+C42 -> 8430.8
B11: Renta
B12: Compras
B13: Electricidad
B14: Gas
B15: Pantry | C15: 1000
B16: Comunicaciones
B17: Publicidad
B18: Insumos de Limpieza
B19: Mantenimiento
B20: Insumos para la tienda
B21: Transporte
B22: Servicios contables
B23: Otros servicios comprados
B24: Total de Gastos | C24: =SUM(C10:C23) -> 9430.8
B27: Salario
B28: Jacqueline
B29: Yeni | C29: 2000
B30: Daniela
B31: Mildrey | C31: 2000
B32: Aileen
B33: Laura
B34: Vanessa
B35: Magaly
B37: 0.02 | C37: =+I4*0.02 -> 4430.8
B42: Total | C42: =SUM(C28:C41) -> 8430.8

Sheet Dia 6
B1: Día: 6
D2: 440 | E2: 440 | F2: 450
B3: VENTAS | C3: TRANSFERENCIAS CUP | D3: TRANSFERENCIAS ZELLE | E3: EURO | F3: USD | G3: EFECTIVO CUP | H3: TRANSFERENCIA A CUENTA FISCAL | I3: TOTAL | J3: TOTAL USD
C4: 22500 | D4: 0 | E4: 0 | F4: 421 | G4: 49800 | H4: 10000 | I4: =+C4+E5+F5+G4+H4+D5 -> 271750 | J4: =+I4/F2 -> 603.88889
D5: =+D4*D2 -> 0 | E5: =+E4*E2 -> 0 | F5: =+F4*F2 -> 189450
B7: Ventas
B8: Ventas Brutas | C8: =+I4 -> 271750
B9: Gastos
B10: Salario | C10: =+C42 -> 31935
B11: Renta
B12: Compras
B13: Electricidad
B14: Gas
B15: Pantry
B16: Comunicaciones
B17: Publicidad
B18: Insumos de Limpieza
B19: Mantenimiento
B20: Insumos para la tienda
B21: Transporte
B22: Servicios contables
B23: Otros servicios comprados
B24: Total de Gastos | C24: =SUM(C10:C23) -> 31935
B27: Salario
B28: Jacqueline | C28: 2000
B29: Yeni
B30: Daniela
B31: Mildrey
B32: Aileen | C32: 2000
B33: Laura
B34: Vanessa
B35: Magaly
B36: Pago Gestora Gercy | C36: =D36*F2 -> 22500 | D36: 50
B37: 0.02 | C37: =+I4*0.02 -> 5435
B42: Total | C42: =SUM(C28:C41) -> 31935

Sheet Dia 7
B1: Día: 7
D2: 440 | E2: 440 | F2: 445
B3: VENTAS | C3: TRANSFERENCIAS CUP | D3: TRANSFERENCIAS ZELLE | E3: EURO | F3: USD | G3: EFECTIVO CUP | H3: TRANSFERENCIA A CUENTA FISCAL | I3: TOTAL | J3: TOTAL USD
C4: 0 | D4: 0 | E4: 0 | F4: 134 | G4: 50730 | H4: 0 | I4: =+C4+E5+F5+G4+H4+D5 -> 110360 | J4: =+I4/F2 -> 248
D5: =+D4*D2 -> 0 | E5: =+E4*E2 -> 0 | F5: =+F4*F2 -> 59630
B7: Ventas
B8: Ventas Brutas | C8: =+I4 -> 110360
B9: Gastos
B10: Salario | C10: =+C42 -> 2207.2
B11: Renta
B12: Compras
B13: Electricidad
B14: Gas
B15: Pantry
B16: Comunicaciones
B17: Publicidad
B18: Insumos de Limpieza
B19: Mantenimiento
B20: Insumos para la tienda
B21: Transporte
B22: Servicios contables
B23: Otros servicios comprados
B24: Total de Gastos | C24: =SUM(C10:C23) -> 2207.2
B27: Salario
B28: Jacqueline
B29: Yeni
B30: Daniela
B31: Mildrey
B32: Aileen
B33: Laura
B34: Vanessa
B35: Magaly
B37: 0.02 | C37: =+I4*0.02 -> 2207.2
B42: Total | C42: =SUM(C28:C41) -> 2207.2

Sheet Dia 8
B1: Día: 8
D2: 440 | E2: 440 | F2: 445
B3: VENTAS | C3: TRANSFERENCIAS CUP | D3: TRANSFERENCIAS ZELLE | E3: EURO | F3: USD | G3: CUP | H3: TRANSFERENCIA A CUENTA FISCAL | I3: TOTAL | J3: TOTAL USD
C4: 0 | D4: 0 | E4: 0 | F4: 445 | G4: 37505 | H4: 0 | I4: =+C4+E5+F5+G4+H4+D5 -> 235530 | J4: =+I4/F2 -> 529.2809
D5: =+D4*D2 -> 0 | E5: =+E4*E2 -> 0 | F5: =+F4*F2 -> 198025
B7: Ventas
B8: Ventas Brutas | C8: =+I4 -> 235530
B9: Gastos
B10: Salario | C10: =+C42 -> 8710.6
B11: Renta
B12: Compras
B13: Electricidad
B14: Gas
B15: Pantry
B16: Comunicaciones
B17: Publicidad
B18: Insumos de Limpieza
B19: Mantenimiento
B20: Insumos para la tienda
B21: Transporte
B22: Servicios contables
B23: Otros servicios comprados
B24: Total de Gastos | C24: =SUM(C10:C23) -> 8710.6
B27: Salario
B28: Jacqueline | C28: 2000
B29: Yeni
B30: Daniela
B31: Mildrey
B32: Aileen | C32: 2000
B33: Laura
B34: Vanessa
B35: Magaly
B37: 0.02 | C37: =+I4*0.02 -> 4710.6
B42: Total | C42: =SUM(C28:C41) -> 8710.6

Sheet Dia 9
B1: Día: 9
D2: 440 | E2: 440 | F2: 445
B3: VENTAS | C3: TRANSFERENCIAS CUP | D3: TRANSFERENCIAS ZELLE | E3: EURO | F3: USD | G3: CUP | H3: TRANSFERENCIA A CUENTA FISCAL | I3: TOTAL | J3: TOTAL USD
C4: 0 | D4: 0 | E4: 0 | F4: 112 | G4: 37825 | H4: 0 | I4: =+C4+E5+F5+G4+H4+D5 -> 87665 | J4: =+I4/F2 -> 197
D5: =+D4*D2 -> 0 | E5: =+E4*E2 -> 0 | F5: =+F4*F2 -> 49840
B7: Ventas
B8: Ventas Brutas | C8: =+I4 -> 87665
B9: Gastos
B10: Salario | C10: =+C42 -> 7153.3
B11: Renta
B12: Compras
B13: Electricidad
B14: Gas
B15: Pantry
B16: Comunicaciones
B17: Publicidad
B18: Insumos de Limpieza
B19: Mantenimiento
B20: Insumos para la tienda
B21: Transporte
B22: Servicios contables
B23: Otros servicios comprados
B24: Total de Gastos | C24: =SUM(C10:C23) -> 7153.3
B27: Salario
B28: Jacqueline
B29: Yeni | C29: 2000
B30: Daniela | C30: 2000
B31: Mildrey
B32: Aileen
B33: Laura
B34: Vanessa
B35: Magaly
B36: Transporte | C36: 1400
B37: 0.02 | C37: =+I4*0.02 -> 1753.3
B42: Total | C42: =SUM(C28:C41) -> 7153.3

Sheet Dia 10
B1: Día: 10
D2: 440 | E2: 440 | F2: 445
B3: VENTAS | C3: TRANSFERENCIAS CUP | D3: TRANSFERENCIAS ZELLE | E3: EURO | F3: USD | G3: CUP | H3: TRANSFERENCIA A CUENTA FISCAL | I3: TOTAL | J3: TOTAL USD
C4: 0 | D4: 0 | E4: 0 | F4: 275 | G4: 32550 | H4: 0 | I4: =+C4+E5+F5+G4+H4+D5 -> 154925 | J4: =+I4/F2 -> 348.14607
D5: =+D4*D2 -> 0 | E5: =+E4*E2 -> 0 | F5: =+F4*F2 -> 122375
B7: Ventas
B8: Ventas Brutas | C8: =+I4 -> 154925
B9: Gastos
B10: Salario | C10: =+C42 -> 7098.5
B11: Renta
B12: Compras
B13: Electricidad
B14: Gas
B15: Pantry
B16: Comunicaciones
B17: Publicidad
B18: Insumos de Limpieza
B19: Mantenimiento
B20: Insumos para la tienda
B21: Transporte
B22: Servicios contables
B23: Otros servicios comprados
B24: Total de Gastos | C24: =SUM(C10:C23) -> 7098.5
B27: Salario
B28: Jacqueline
B29: Yeni | C29: 2000
B30: Daniela
B31: Mildrey
B32: Aileen | C32: 2000
B33: Laura
B34: Vanessa
B35: Magaly
B37: 0.02 | C37: =+I4*0.02 -> 3098.5
B42: Total | C42: =SUM(C28:C41) -> 7098.5

Sheet Dia 11
B1: Día: 11
D2: 440 | E2: 440 | F2: 450
B3: VENTAS | C3: TRANSFERENCIAS CUP | D3: TRANSFERENCIAS ZELLE | E3: EURO | F3: USD | G3: CUP | H3: TRANSFERENCIA A CUENTA FISCAL | I3: TOTAL | J3: TOTAL USD
C4: 0 | D4: 0 | E4: 0 | F4: 901 | G4: 61275 | H4: 10500 | I4: =+C4+E5+F5+G4+H4+D5 -> 477225 | J4: =+I4/F2 -> 1060.5
D5: =+D4*D2 -> 0 | E5: =+E4*E2 -> 0 | F5: =+F4*F2 -> 405450
B7: Ventas
B8: Ventas Brutas | C8: =+I4 -> 477225
B9: Gastos
B10: Salario | C10: =+C42 -> 13544.5
B11: Renta
B12: Compras
B13: Electricidad
B14: Gas
B15: Pantry
B16: Comunicaciones
B17: Publicidad
B18: Insumos de Limpieza
B19: Mantenimiento
B20: Insumos para la tienda
B21: Transporte
B22: Servicios contables
B23: Otros servicios comprados
B24: Total de Gastos | C24: =SUM(C10:C23) -> 13544.5
B27: Salario
B28: Jacqueline
B29: Yeni | C29: 2000
B30: Daniela
B31: Mildrey
B32: Aileen | C32: 2000
B33: Laura
B34: Vanessa
B35: Magaly
B37: 0.02 | C37: =+I4*0.02 -> 9544.5
B42: Total | C42: =SUM(C28:C41) -> 13544.5

Sheet Dia 12
B1: Día: 12
D2: 440 | E2: 440 | F2: 440
B3: VENTAS | C3: TRANSFERENCIAS CUP | D3: TRANSFERENCIAS ZELLE | E3: EURO | F3: USD | G3: CUP | H3: TRANSFERENCIA A CUENTA FISCAL | I3: TOTAL | J3: TOTAL USD
C4: 6600 | D4: 0 | E4: 0 | F4: 788 | G4: 14950 | H4: 16720 | I4: =+C4+E5+F5+G4+H4+D5 -> 384990 | J4: =+I4/F2 -> 874.97727
D5: =+D4*D2 -> 0 | E5: =+E4*E2 -> 0 | F5: =+F4*F2 -> 346720
B7: Ventas
B8: Ventas Brutas | C8: =+I4 -> 384990
B9: Gastos
B10: Salario | C10: =+C42 -> 11699.8
B11: Renta
B12: Compras
B13: Electricidad
B14: Gas
B15: Pantry
B16: Comunicaciones
B17: Publicidad
B18: Insumos de Limpieza
B19: Mantenimiento
B20: Insumos para la tienda
B21: Transporte
B22: Servicios contables
B23: Otros servicios comprados
B24: Total de Gastos | C24: =SUM(C10:C23) -> 11699.8
B27: Salario
B28: Jacqueline | C28: 2000
B29: Yeni
B30: Daniela | C30: 2000
B31: Mildrey
B32: Aileen
B33: Laura
B34: Vanessa
B35: Magaly
B37: 0.02 | C37: =+I4*0.02 -> 7699.8
B42: Total | C42: =SUM(C28:C41) -> 11699.8

Sheet Dia 13
B1: Día: 13
D2: 440 | E2: 440 | F2: 440
B3: VENTAS | C3: TRANSFERENCIAS CUP | D3: TRANSFERENCIAS ZELLE | E3: EURO | F3: USD | G3: CUP | H3: TRANSFERENCIA A CUENTA FISCAL | I3: TOTAL | J3: TOTAL USD
C4: 0 | D4: 0 | E4: 165 | F4: 957 | G4: 7000 | H4: 0 | I4: =+C4+E5+F5+G4+H4+D5 -> 500680 | J4: =+I4/F2 -> 1137.9091
D5: =+D4*D2 -> 0 | E5: =+E4*E2 -> 72600 | F5: =+F4*F2 -> 421080
B7: Ventas
B8: Ventas Brutas | C8: =+I4 -> 500680
B9: Gastos
B10: Salario | C10: =+C42 -> 14013.6
B11: Renta
B12: Compras
B13: Electricidad
B14: Gas
B15: Pantry
B16: Comunicaciones
B17: Publicidad
B18: Insumos de Limpieza
B19: Mantenimiento
B20: Insumos para la tienda
B21: Transporte
B22: Servicios contables
B23: Otros servicios comprados
B24: Total de Gastos | C24: =SUM(C10:C23) -> 14013.6
B27: Salario
B28: Jacqueline | C28: 2000
B29: Yeni
B30: Daniela | C30: 2000
B31: Mildrey
B32: Aileen
B33: Laura
B34: Vanessa
B35: Magaly
B37: 0.02 | C37: =+I4*0.02 -> 10013.6
B42: Total | C42: =SUM(C28:C41) -> 14013.6

Sheet Dia 14
B1: Día: 14
D2: 440 | E2: 440 | F2: 440
B3: VENTAS | C3: TRANSFERENCIAS CUP | D3: TRANSFERENCIAS ZELLE | E3: EURO | F3: USD | G3: EFECTIVO | H3: TRANSFERENCIA A CUENTA FISCAL | I3: TOTAL | J3: TOTAL USD
C4: 7920 | D4: 0 | E4: 0 | F4: 489 | G4: 17600 | H4: 11000 | I4: =+C4+E5+F5+G4+H4+D5 -> 251680 | J4: =+I4/F2 -> 572
D5: =+D4*D2 -> 0 | E5: =+E4*E2 -> 0 | F5: =+F4*F2 -> 215160
B7: Ventas
B8: Ventas Brutas | C8: =+I4 -> 251680
B9: Gastos
B10: Salario | C10: =+C42 -> 9033.6
B11: Renta
B12: Compras
B13: Electricidad
B14: Gas
B15: Pantry
B16: Comunicaciones
B17: Publicidad
B18: Insumos de Limpieza
B19: Mantenimiento
B20: Insumos para la tienda
B21: Transporte
B22: Servicios contables
B23: Otros servicios comprados
B24: Total de Gastos | C24: =SUM(C10:C23) -> 9033.6
B27: Salario
B28: Jacqueline | C28: 2000
B29: Yeni
B30: Daniela | C30: 2000
B31: Mildrey
B32: Aileen
B33: Laura
B34: Vanessa
B35: Magaly
B37: 0.02 | C37: =+I4*0.02 -> 5033.6
B42: Total | C42: =SUM(C28:C41) -> 9033.6

Sheet Dia 15
B1: Día: 15
D2: 440 | E2: 440 | F2: 440
B3: VENTAS | C3: TRANSFERENCIAS CUP | D3: TRANSFERENCIAS ZELLE | E3: EURO | F3: USD | G3: EFECTIVO | H3: TRANSFERENCIA A CUENTA FISCAL | I3: TOTAL | J3: TOTAL USD
C4: 0 | D4: 0 | E4: 0 | F4: 471.4 | G4: 0 | H4: 0 | I4: =+C4+E5+F5+G4+H4+D5 -> 207416 | J4: =+I4/F2 -> 471.4
D5: =+D4*D2 -> 0 | E5: =+E4*E2 -> 0 | F5: =+F4*F2 -> 207416
B7: Ventas
B8: Ventas Brutas | C8: =+I4 -> 207416
B9: Gastos
B10: Salario | C10: =+C42 -> 20908.32
B11: Renta
B12: Compras
B13: Electricidad
B14: Gas
B15: Pantry
B16: Comunicaciones
B17: Publicidad
B18: Insumos de Limpieza
B19: Mantenimiento
B20: Insumos para la tienda
B21: Transporte
B22: Servicios contables
B23: Otros servicios comprados
B24: Total de Gastos | C24: =SUM(C10:C23) -> 20908.32
B27: Salario
B28: Jacqueline
B29: Yeni | C29: 2000
B30: Daniela
B31: Mildrey | C31: 2000
B32: Aileen
B33: Laura | C33: =D33*F2 -> 8800 | D33: 20
B34: Vanessa
B35: Magaly
B36: Pago Gestor Yeni | C36: =D36*F2 -> 3960 | D36: 9
B37: 0.02 | C37: =+I4*0.02 -> 4148.32
B42: Total | C42: =SUM(C28:C41) -> 20908.32

Sheet Dia 16
B1: Día: 16
D2: 440 | E2: 440 | F2: 440
B3: VENTAS | C3: TRANSFERENCIAS CUP | D3: TRANSFERENCIAS ZELLE | E3: EURO | F3: USD | G3: CUP | H3: TRANSFERENCIA A CUENTA FISCAL | I3: TOTAL | J3: TOTAL USD
C4: 0 | D4: 0 | E4: 0 | F4: 504 | G4: 22000 | H4: 0 | I4: =+C4+E5+F5+G4+H4+D5 -> 243760 | J4: =+I4/F2 -> 554
D5: =+D4*D2 -> 0 | E5: =+E4*E2 -> 0 | F5: =+F4*F2 -> 221760
B7: Ventas
B8: Ventas Brutas | C8: =+I4 -> 243760
B9: Gastos
B10: Salario | C10: =+C42 -> 8875.2
B11: Renta
B12: Compras
B13: Electricidad
B14: Gas
B15: Pantry
B16: Comunicaciones
B17: Publicidad
B18: Insumos de Limpieza
B19: Mantenimiento
B20: Insumos para la tienda
B21: Transporte
B22: Servicios contables
B23: Otros servicios comprados
B24: Total de Gastos | C24: =SUM(C10:C23) -> 8875.2
B27: Salario
B28: Jacqueline
B29: Yeni | C29: 2000
B30: Daniela
B31: Mildrey | C31: 2000
B32: Aileen
B33: Laura
B34: Vanessa
B35: Magaly
B37: 0.02 | C37: =+I4*0.02 -> 4875.2
B42: Total | C42: =SUM(C28:C41) -> 8875.2

Sheet Dia 17
B1: Día: 17
D2: 440 | E2: 440 | F2: 440
B3: VENTAS | C3: TRANSFERENCIAS CUP | D3: TRANSFERENCIAS ZELLE | E3: EURO | F3: USD | G3: EFECTIVO | H3: TRANSFERENCIA A CUENTA FISCAL | I3: TOTAL | J3: TOTAL USD
C4: 39920 | D4: 0 | E4: 0 | F4: 445 | G4: 154120 | H4: 0 | I4: =+C4+E5+F5+G4+H4+D5 -> 389840 | J4: =+I4/F2 -> 886
D5: =+D4*D2 -> 0 | E5: =+E4*E2 -> 0 | F5: =+F4*F2 -> 195800
B7: Ventas
B8: Ventas Brutas | C8: =+I4 -> 389840
B9: Gastos
B10: Salario | C10: =+C42 -> 11796.8
B11: Renta
B12: Compras
B13: Electricidad
B14: Gas
B15: Pantry
B16: Comunicaciones
B17: Publicidad
B18: Insumos de Limpieza
B19: Mantenimiento
B20: Insumos para la tienda
B21: Transporte
B22: Servicios contables
B23: Otros servicios comprados
B24: Total de Gastos | C24: =SUM(C10:C23) -> 11796.8
B27: Salario
B28: Jacqueline
B29: Yeni | C29: 2000
B30: Daniela
B31: Mildrey | C31: 2000
B32: Aileen
B33: Laura
B34: Vanessa
B35: Magaly
B37: 0.02 | C37: =+I4*0.02 -> 7796.8
B42: Total | C42: =SUM(C28:C41) -> 11796.8

Sheet Dia 18
B1: Día: 18
D2: 440 | E2: 440 | F2: 420
B3: VENTAS | C3: TRANSFERENCIAS CUP | D3: TRANSFERENCIAS ZELLE | E3: EURO | F3: USD | G3: EFECTIVO | H3: TRANSFERENCIA A CUENTA FISCAL | I3: TOTAL | J3: TOTAL USD
C4: 0 | D4: 0 | E4: 50 | F4: 224 | G4: 0 | H4: 0 | I4: =+C4+E5+F5+G4+H4+D5 -> 116080 | J4: =+I4/F2 -> 276.38095
D5: =+D4*D2 -> 0 | E5: =+E4*E2 -> 22000 | F5: =+F4*F2 -> 94080
B7: Ventas
B8: Ventas Brutas | C8: =+I4 -> 116080
B9: Gastos
B10: Salario | C10: =+C42 -> 56721.6
B11: Renta
B12: Compras
B13: Electricidad
B14: Gas
B15: Pantry
B16: Comunicaciones
B17: Publicidad
B18: Insumos de Limpieza
B19: Mantenimiento
B20: Insumos para la tienda
B21: Transporte
B22: Servicios contables
B23: Otros servicios comprados
B24: Total de Gastos | C24: =SUM(C10:C23) -> 56721.6
B27: Salario
B28: Jacqueline | C28: 2000
B29: Yeni
B30: Daniela
B31: Mildrey
B32: Aileen | C32: 2000
B33: Laura | C33: =D33*F2 -> 8400 | D33: 20
B34: Vanessa
B35: Magaly
B36: Saqué yo | C36: =D36*F2 -> 42000 | D36: 100
B37: 0.02 | C37: =+I4*0.02 -> 2321.6
B42: Total | C42: =SUM(C28:C41) -> 56721.6

Sheet Dia 19
B1: Día: 19
D2: 440 | E2: 440 | F2: 460
B3: VENTAS | C3: TRANSFERENCIAS CUP | D3: TRANSFERENCIAS ZELLE | E3: EURO | F3: USD | G3: EFECTIVO | H3: TRANSFERENCIA A CUENTA FISCAL | I3: TOTAL | J3: TOTAL USD
C4: 0 | D4: 0 | E4: 0 | F4: 0 | G4: 0 | H4: 0 | I4: =+C4+E5+F5+G4+H4+D5 -> 0 | J4: =+I4/F2 -> 0
D5: =+D4*D2 -> 0 | E5: =+E4*E2 -> 0 | F5: =+F4*F2 -> 0
B7: Ventas
B8: Ventas Brutas | C8: =+I4 -> 0
B9: Gastos
B10: Salario | C10: =+C42 -> 0
B11: Renta
B12: Compras
B13: Electricidad
B14: Gas
B15: Pantry
B16: Comunicaciones
B17: Publicidad
B18: Insumos de Limpieza
B19: Mantenimiento
B20: Insumos para la tienda
B21: Transporte
B22: Servicios contables
B23: Otros servicios comprados
B24: Total de Gastos | C24: =SUM(C10:C23) -> 0
B27: Salario
B28: Jacqueline
B29: Yeni
B30: Daniela
B31: Mildrey
B32: Aileen
B33: Laura
B34: Vanessa
B35: Magaly
B37: 0.02 | C37: =+I4*0.02 -> 0
B42: Total | C42: =SUM(C28:C41) -> 0

Sheet Dia 20
B1: Día: 20
D2: 440 | E2: 440 | F2: 440
B3: VENTAS | C3: TRANSFERENCIAS CUP | D3: TRANSFERENCIAS ZELLE | E3: EURO | F3: USD | G3: EFECTIVO | H3: TRANSFERENCIA A CUENTA FISCAL | I3: TOTAL | J3: TOTAL USD
C4: 0 | D4: 0 | E4: 0 | F4: 772 | G4: 30450 | H4: 0 | I4: =+C4+E5+F5+G4+H4+D5 -> 370130 | J4: =+I4/F2 -> 841.20455
D5: =+D4*D2 -> 0 | E5: =+E4*E2 -> 0 | F5: =+F4*F2 -> 339680
B7: Ventas
B8: Ventas Brutas | C8: =+I4 -> 370130
B9: Gastos
B10: Salario | C10: =+C42 -> 11402.6
B11: Renta
B12: Compras
B13: Electricidad
B14: Gas
B15: Pantry
B16: Comunicaciones
B17: Publicidad
B18: Insumos de Limpieza
B19: Mantenimiento
B20: Insumos para la tienda
B21: Transporte
B22: Servicios contables
B23: Otros servicios comprados
B24: Total de Gastos | C24: =SUM(C10:C23) -> 11402.6
B27: Salario
B28: Jacqueline | C28: 2000
B29: Yeni
B30: Daniela
B31: Mildrey
B32: Aileen | C32: 2000
B33: Laura
B34: Vanessa
B35: Magaly
B37: 0.02 | C37: =+I4*0.02 -> 7402.6
B42: Total | C42: =SUM(C28:C41) -> 11402.6

Sheet Dia 21
B1: Día: 21
D2: 440 | E2: 440 | F2: 440
B3: VENTAS | C3: TRANSFERENCIAS CUP | D3: TRANSFERENCIAS ZELLE | E3: EURO | F3: USD | G3: EFECTIVO | H3: TRANSFERENCIA A CUENTA FISCAL | I3: TOTAL | J3: TOTAL USD
C4: 0 | D4: 0 | E4: 0 | F4: 412 | G4: 46450 | H4: 0 | I4: =+C4+E5+F5+G4+H4+D5 -> 227730 | J4: =+I4/F2 -> 517.56818
D5: =+D4*D2 -> 0 | E5: =+E4*E2 -> 0 | F5: =+F4*F2 -> 181280
B7: Ventas
B8: Ventas Brutas | C8: =+I4 -> 227730
B9: Gastos
B10: Salario | C10: =+C42 -> 4554.6
B11: Renta
B12: Compras
B13: Electricidad
B14: Gas
B15: Pantry
B16: Comunicaciones
B17: Publicidad
B18: Insumos de Limpieza
B19: Mantenimiento
B20: Insumos para la tienda
B21: Transporte
B22: Servicios contables
B23: Otros servicios comprados
B24: Total de Gastos | C24: =SUM(C10:C23) -> 4554.6
B27: Salario
B28: Jacqueline
B29: Yeni
B30: Daniela
B31: Mildrey
B32: Aileen
B33: Laura
B34: Vanessa
B35: Magaly
B37: 0.02 | C37: =+I4*0.02 -> 4554.6
B42: Total | C42: =SUM(C28:C41) -> 4554.6

Sheet Dia 22
B1: Día: 22
D2: 440 | E2: 440 | F2: 440
B3: VENTAS | C3: TRANSFERENCIAS CUP | D3: TRANSFERENCIAS ZELLE | E3: EURO | F3: USD | G3: EFECTIVO | H3: TRANSFERENCIA A CUENTA FISCAL | I3: TOTAL | J3: TOTAL USD
C4: 0 | D4: 0 | E4: 0 | F4: 222 | G4: 60940 | H4: 0 | I4: =+C4+E5+F5+G4+H4+D5 -> 158620 | J4: =+I4/F2 -> 360.5
D5: =+D4*D2 -> 0 | E5: =+E4*E2 -> 0 | F5: =+F4*F2 -> 97680
B7: Ventas
B8: Ventas Brutas | C8: =+I4 -> 158620
B9: Gastos
B10: Salario | C10: =+C42 -> 7172.4
B11: Renta
B12: Compras
B13: Electricidad
B14: Gas
B15: Pantry
B16: Comunicaciones
B17: Publicidad
B18: Insumos de Limpieza
B19: Mantenimiento
B20: Insumos para la tienda
B21: Transporte
B22: Servicios contables
B23: Otros servicios comprados
B24: Total de Gastos | C24: =SUM(C10:C23) -> 7172.4
B27: Salario
B28: Jacqueline
B29: Yeni | C29: 2000
B30: Daniela
B31: Mildrey | C31: 2000
B32: Aileen
B33: Laura
B34: Vanessa
B35: Magaly
B37: 0.02 | C37: =+I4*0.02 -> 3172.4
B42: Total | C42: =SUM(C28:C41) -> 7172.4

Sheet Dia 23
B1: Día: 23
D2: 440 | E2: 440 | F2: 460
B3: VENTAS | C3: TRANSFERENCIAS CUP | D3: TRANSFERENCIAS ZELLE | E3: EURO | F3: USD | G3: EFECTIVO | H3: TRANSFERENCIA A CUENTA FISCAL | I3: TOTAL | J3: TOTAL USD
C4: 0 | D4: 0 | E4: 0 | F4: 0 | G4: 0 | H4: 0 | I4: =+C4+E5+F5+G4+H4+D5 -> 0 | J4: =+I4/F2 -> 0
D5: =+D4*D2 -> 0 | E5: =+E4*E2 -> 0 | F5: =+F4*F2 -> 0
B7: Ventas
B8: Ventas Brutas | C8: =+I4 -> 0
B9: Gastos
B10: Salario | C10: =+C42 -> 0
B11: Renta
B12: Compras
B13: Electricidad
B14: Gas
B15: Pantry
B16: Comunicaciones
B17: Publicidad
B18: Insumos de Limpieza
B19: Mantenimiento
B20: Insumos para la tienda
B21: Transporte
B22: Servicios contables
B23: Otros servicios comprados
B24: Total de Gastos | C24: =SUM(C10:C23) -> 0
B27: Salario
B28: Jacqueline
B29: Yeni
B30: Daniela
B31: Mildrey
B32: Aileen
B33: Laura
B34: Vanessa
B35: Magaly
B37: 0.02 | C37: =+I4*0.02 -> 0
B42: Total | C42: =SUM(C28:C41) -> 0

Sheet Dia 24
B1: Día: 24
D2: 440 | E2: 440 | F2: 460
B3: VENTAS | C3: TRANSFERENCIAS CUP | D3: TRANSFERENCIAS ZELLE | E3: EURO | F3: USD | G3: EFECTIVO | H3: TRANSFERENCIA A CUENTA FISCAL | I3: TOTAL | J3: TOTAL USD
C4: 0 | D4: 0 | E4: 0 | F4: 0 | G4: 0 | H4: 0 | I4: =+C4+E5+F5+G4+H4+D5 -> 0 | J4: =+I4/F2 -> 0
D5: =+D4*D2 -> 0 | E5: =+E4*E2 -> 0 | F5: =+F4*F2 -> 0
B7: Ventas
B8: Ventas Brutas | C8: =+I4 -> 0
B9: Gastos
B10: Salario | C10: =+C42 -> 0
B11: Renta
B12: Compras
B13: Electricidad
B14: Gas
B15: Pantry
B16: Comunicaciones
B17: Publicidad
B18: Insumos de Limpieza
B19: Mantenimiento
B20: Insumos para la tienda
B21: Transporte
B22: Servicios contables
B23: Otros servicios comprados
B24: Total de Gastos | C24: =SUM(C10:C23) -> 0
B27: Salario
B28: Jacqueline
B29: Yeni
B30: Daniela
B31: Mildrey
B32: Aileen
B33: Laura
B34: Vanessa
B35: Magaly
B37: 0.02 | C37: =+I4*0.02 -> 0
B42: Total | C42: =SUM(C28:C41) -> 0

Sheet Dia 25
B1: Día: 25
D2: 440 | E2: 440 | F2: 460
B3: VENTAS | C3: TRANSFERENCIAS CUP | D3: TRANSFERENCIAS ZELLE | E3: EURO | F3: USD | G3: EFECTIVO | H3: TRANSFERENCIA A CUENTA FISCAL | I3: TOTAL | J3: TOTAL USD
C4: 0 | D4: 0 | E4: 0 | F4: 0 | G4: 0 | H4: 0 | I4: =+C4+E5+F5+G4+H4+D5 -> 0 | J4: =+I4/F2 -> 0
D5: =+D4*D2 -> 0 | E5: =+E4*E2 -> 0 | F5: =+F4*F2 -> 0
B7: Ventas
B8: Ventas Brutas | C8: =+I4 -> 0
B9: Gastos
B10: Salario | C10: =+C42 -> 0
B11: Renta
B12: Compras
B13: Electricidad
B14: Gas
B15: Pantry
B16: Comunicaciones
B17: Publicidad
B18: Insumos de Limpieza
B19: Mantenimiento
B20: Insumos para la tienda
B21: Transporte
B22: Servicios contables
B23: Otros servicios comprados
B24: Total de Gastos | C24: =SUM(C10:C23) -> 0
B27: Salario
B28: Jacqueline
B29: Yeni
B30: Daniela
B31: Mildrey
B32: Aileen
B33: Laura
B34: Vanessa
B35: Magaly
B37: 0.02 | C37: =+I4*0.02 -> 0
B42: Total | C42: =SUM(C28:C41) -> 0

Sheet Dia 26
B1: Día: 26
D2: 440 | E2: 440 | F2: 460
B3: VENTAS | C3: TRANSFERENCIAS CUP | D3: TRANSFERENCIAS ZELLE | E3: EURO | F3: USD | G3: EFECTIVO | H3: TRANSFERENCIA A CUENTA FISCAL | I3: TOTAL | J3: TOTAL USD
C4: 0 | D4: 0 | E4: 0 | F4: 0 | G4: 0 | H4: 0 | I4: =+C4+E5+F5+G4+H4+D5 -> 0 | J4: =+I4/F2 -> 0
D5: =+D4*D2 -> 0 | E5: =+E4*E2 -> 0 | F5: =+F4*F2 -> 0
B7: Ventas
B8: Ventas Brutas | C8: =+I4 -> 0
B9: Gastos
B10: Salario | C10: =+C42 -> 0
B11: Renta
B12: Compras
B13: Electricidad
B14: Gas
B15: Pantry
B16: Comunicaciones
B17: Publicidad
B18: Insumos de Limpieza
B19: Mantenimiento
B20: Insumos para la tienda
B21: Transporte
B22: Servicios contables
B23: Otros servicios comprados
B24: Total de Gastos | C24: =SUM(C10:C23) -> 0
B27: Salario
B28: Jacqueline
B29: Yeni
B30: Daniela
B31: Mildrey
B32: Aileen
B33: Laura
B34: Vanessa
B35: Magaly
B37: 0.02 | C37: =+I4*0.02 -> 0
B42: Total | C42: =SUM(C28:C41) -> 0

Sheet Dia 27
B1: Día: 27
D2: 440 | E2: 440 | F2: 460
B3: VENTAS | C3: TRANSFERENCIAS CUP | D3: TRANSFERENCIAS ZELLE | E3: EURO | F3: USD | G3: EFECTIVO | H3: TRANSFERENCIA A CUENTA FISCAL | I3: TOTAL | J3: TOTAL USD
C4: 0 | D4: 0 | E4: 0 | F4: 0 | G4: 0 | H4: 0 | I4: =+C4+E5+F5+G4+H4+D5 -> 0 | J4: =+I4/F2 -> 0
D5: =+D4*D2 -> 0 | E5: =+E4*E2 -> 0 | F5: =+F4*F2 -> 0
B7: Ventas
B8: Ventas Brutas | C8: =+I4 -> 0
B9: Gastos
B10: Salario | C10: =+C42 -> 0
B11: Renta
B12: Compras
B13: Electricidad
B14: Gas
B15: Pantry
B16: Comunicaciones
B17: Publicidad
B18: Insumos de Limpieza
B19: Mantenimiento
B20: Insumos para la tienda
B21: Transporte
B22: Servicios contables
B23: Otros servicios comprados
B24: Total de Gastos | C24: =SUM(C10:C23) -> 0
B27: Salario
B28: Jacqueline
B29: Yeni
B30: Daniela
B31: Mildrey
B32: Aileen
B33: Laura
B34: Vanessa
B35: Magaly
B37: 0.02 | C37: =+I4*0.02 -> 0
B42: Total | C42: =SUM(C28:C41) -> 0

Sheet Dia 28
B1: Día: 28
D2: 440 | E2: 440 | F2: 460
B3: VENTAS | C3: TRANSFERENCIAS CUP | D3: TRANSFERENCIAS ZELLE | E3: EURO | F3: USD | G3: EFECTIVO | H3: TRANSFERENCIA A CUENTA FISCAL | I3: TOTAL | J3: TOTAL USD
C4: 0 | D4: 0 | E4: 0 | F4: 0 | G4: 0 | H4: 0 | I4: =+C4+E5+F5+G4+H4+D5 -> 0 | J4: =+I4/F2 -> 0
D5: =+D4*D2 -> 0 | E5: =+E4*E2 -> 0 | F5: =+F4*F2 -> 0
B7: Ventas
B8: Ventas Brutas | C8: =+I4 -> 0
B9: Gastos
B10: Salario | C10: =+C42 -> 0
B11: Renta
B12: Compras
B13: Electricidad
B14: Gas
B15: Pantry
B16: Comunicaciones
B17: Publicidad
B18: Insumos de Limpieza
B19: Mantenimiento
B20: Insumos para la tienda
B21: Transporte
B22: Servicios contables
B23: Otros servicios comprados
B24: Total de Gastos | C24: =SUM(C10:C23) -> 0
B27: Salario
B28: Jacqueline
B29: Yeni
B30: Daniela
B31: Mildrey
B32: Aileen
B33: Laura
B34: Vanessa
B35: Magaly
B37: 0.02 | C37: =+I4*0.02 -> 0
B42: Total | C42: =SUM(C28:C41) -> 0

Sheet Dia 29
B1: Día: 29
D2: 440 | E2: 440 | F2: 460
B3: VENTAS | C3: TRANSFERENCIAS CUP | D3: TRANSFERENCIAS ZELLE | E3: EURO | F3: USD | G3: EFECTIVO | H3: TRANSFERENCIA A CUENTA FISCAL | I3: TOTAL | J3: TOTAL USD
C4: 0 | D4: 0 | E4: 0 | F4: 0 | G4: 0 | H4: 0 | I4: =+C4+E5+F5+G4+H4+D5 -> 0 | J4: =+I4/F2 -> 0
D5: =+D4*D2 -> 0 | E5: =+E4*E2 -> 0 | F5: =+F4*F2 -> 0
B7: Ventas
B8: Ventas Brutas | C8: =+I4 -> 0
B9: Gastos
B10: Salario | C10: =+C42 -> 0
B11: Renta
B12: Compras
B13: Electricidad
B14: Gas
B15: Pantry
B16: Comunicaciones
B17: Publicidad
B18: Insumos de Limpieza
B19: Mantenimiento
B20: Insumos para la tienda
B21: Transporte
B22: Servicios contables
B23: Otros servicios comprados
B24: Total de Gastos | C24: =SUM(C10:C23) -> 0
B27: Salario
B28: Jacqueline
B29: Yeni
B30: Daniela
B31: Mildrey
B32: Aileen
B33: Laura
B34: Vanessa
B35: Magaly
B37: 0.02 | C37: =+I4*0.02 -> 0
B42: Total | C42: =SUM(C28:C41) -> 0

Sheet Dia 30
B1: Día: 30
D2: 440 | E2: 440 | F2: 460
B3: VENTAS | C3: TRANSFERENCIAS CUP | D3: TRANSFERENCIAS ZELLE | E3: EURO | F3: USD | G3: EFECTIVO | H3: TRANSFERENCIA A CUENTA FISCAL | I3: TOTAL | J3: TOTAL USD
C4: 0 | D4: 0 | E4: 0 | F4: 0 | G4: 0 | H4: 0 | I4: =+C4+E5+F5+G4+H4+D5 -> 0 | J4: =+I4/F2 -> 0
D5: =+D4*D2 -> 0 | E5: =+E4*E2 -> 0 | F5: =+F4*F2 -> 0
B7: Ventas
B8: Ventas Brutas | C8: =+I4 -> 0
B9: Gastos
B10: Salario | C10: =+C42 -> 0
B11: Renta
B12: Compras
B13: Electricidad
B14: Gas
B15: Pantry
B16: Comunicaciones
B17: Publicidad
B18: Insumos de Limpieza
B19: Mantenimiento
B20: Insumos para la tienda
B21: Transporte
B22: Servicios contables
B23: Otros servicios comprados
B24: Total de Gastos | C24: =SUM(C10:C23) -> 0
B27: Salario
B28: Jacqueline
B29: Yeni
B30: Daniela
B31: Mildrey
B32: Aileen
B33: Laura
B34: Vanessa
B35: Magaly
B37: 0.02 | C37: =+I4*0.02 -> 0
B42: Total | C42: =SUM(C28:C41) -> 0

Sheet Dia 31
B1: Día: 31
D2: 440 | E2: 440 | F2: 460
B3: VENTAS | C3: TRANSFERENCIAS CUP | D3: TRANSFERENCIAS ZELLE | E3: EURO | F3: USD | G3: EFECTIVO | H3: TRANSFERENCIA A CUENTA FISCAL | I3: TOTAL | J3: TOTAL USD
C4: 0 | D4: 0 | E4: 0 | F4: 0 | G4: 0 | H4: 0 | I4: =+C4+E5+F5+G4+H4+D5 -> 0 | J4: =+I4/F2 -> 0
D5: =+D4*D2 -> 0 | E5: =+E4*E2 -> 0 | F5: =+F4*F2 -> 0
B7: Ventas
B8: Ventas Brutas | C8: =+I4 -> 0
B9: Gastos
B10: Salario | C10: =+C42 -> 0
B11: Renta
B12: Compras
B13: Electricidad
B14: Gas
B15: Pantry
B16: Comunicaciones
B17: Publicidad
B18: Insumos de Limpieza
B19: Mantenimiento
B20: Insumos para la tienda
B21: Transporte
B22: Servicios contables
B23: Otros servicios comprados
B24: Total de Gastos | C24: =SUM(C10:C23) -> 0
B27: Salario
B28: Jacqueline
B29: Yeni
B30: Daniela
B31: Mildrey
B32: Aileen
B33: Laura
B34: Vanessa
B35: Magaly
B37: 0.02 | C37: =+I4*0.02 -> 0
B42: Total | C42: =SUM(C28:C41) -> 0

Sheet Mes
B3: MES:
B6: Ventas Brutas | C6: =+Ventas!J35 -> 4931187
B7: 10% ventas | C7: =+C6*0.1 -> 493118.7
B8: 5% Ingresos personales | C8: =+(C6-3260)*0.05 -> 246396.35
B9: Ventas Netas | C9: =+C6-C7-C8 -> 4191672
B10: Gastos | D10: % del total de gastos
B11: Salario | C11: =+'Dia 1'!C10+'Dia 2'!C10+'Dia 3'!C10+'Dia 4'!C10+'Dia 5'!C10+'Dia 6'!C10+'Dia 7'!C10+'Dia 8'!C10+'Dia 9'!C10+'Dia 10'!C10+'Dia 11'!C10+'Dia 12'!C10+'Dia 13'!C10+'Dia 14'!C10+'Dia 15'!C10+'Dia 16'!C10+'Dia 17'!C10+'Dia 18'!C10+'Dia 19'!C10+'Dia 20'!C10+'Dia 21'!C10+'Dia 22'!C10+'Dia 23'!C10+'Dia 24'!C10+'Dia 25'!C10+'Dia 26'!C10+'Dia 27'!C10+'Dia 28'!C10+'Dia 29'!C10+'Dia 30'!C10+'Dia 31'!C10 -> 268683.74 | D11: =+C11/$C$25 -> 0.72896254
B12: Renta | C12: =+'Dia 1'!C11+'Dia 2'!C11+'Dia 3'!C11+'Dia 4'!C11+'Dia 5'!C11+'Dia 6'!C11+'Dia 7'!C11+'Dia 8'!C11+'Dia 9'!C11+'Dia 10'!C11+'Dia 11'!C11+'Dia 12'!C11+'Dia 13'!C11+'Dia 14'!C11+'Dia 15'!C11+'Dia 16'!C11+'Dia 17'!C11+'Dia 18'!C11+'Dia 19'!C11+'Dia 20'!C11+'Dia 21'!C11+'Dia 22'!C11+'Dia 23'!C11+'Dia 24'!C11+'Dia 25'!C11+'Dia 26'!C11+'Dia 27'!C11+'Dia 28'!C11+'Dia 29'!C11+'Dia 30'!C11+'Dia 31'!C11 -> 0 | D12: =+C12/$C$25 -> 0
B13: Compras | C13: =+'Dia 1'!C12+'Dia 2'!C12+'Dia 3'!C12+'Dia 4'!C12+'Dia 5'!C12+'Dia 6'!C12+'Dia 7'!C12+'Dia 8'!C12+'Dia 9'!C12+'Dia 10'!C12+'Dia 11'!C12+'Dia 12'!C12+'Dia 13'!C12+'Dia 14'!C12+'Dia 15'!C12+'Dia 16'!C12+'Dia 17'!C12+'Dia 18'!C12+'Dia 19'!C12+'Dia 20'!C12+'Dia 21'!C12+'Dia 22'!C12+'Dia 23'!C12+'Dia 24'!C12+'Dia 25'!C12+'Dia 26'!C12+'Dia 27'!C12+'Dia 28'!C12+'Dia 29'!C12+'Dia 30'!C12+'Dia 31'!C12 -> 0 | D13: =+C13/$C$25 -> 0
B14: Electricidad | C14: =+'Dia 1'!C13+'Dia 2'!C13+'Dia 3'!C13+'Dia 4'!C13+'Dia 5'!C13+'Dia 6'!C13+'Dia 7'!C13+'Dia 8'!C13+'Dia 9'!C13+'Dia 10'!C13+'Dia 11'!C13+'Dia 12'!C13+'Dia 13'!C13+'Dia 14'!C13+'Dia 15'!C13+'Dia 16'!C13+'Dia 17'!C13+'Dia 18'!C13+'Dia 19'!C13+'Dia 20'!C13+'Dia 21'!C13+'Dia 22'!C13+'Dia 23'!C13+'Dia 24'!C13+'Dia 25'!C13+'Dia 26'!C13+'Dia 27'!C13+'Dia 28'!C13+'Dia 29'!C13+'Dia 30'!C13+'Dia 31'!C13 -> 0 | D14: =+C14/$C$25 -> 0
B15: Gas | C15: ='Dia 1'!C14+'Dia 2'!C14+'Dia 3'!C14+'Dia 4'!C14+'Dia 5'!C14+'Dia 6'!C14+'Dia 7'!C14+'Dia 8'!C14+'Dia 9'!C14+'Dia 10'!C14+'Dia 11'!C14+'Dia 12'!C14+'Dia 13'!C14+'Dia 14'!C14+'Dia 15'!C14+'Dia 16'!C14+'Dia 17'!C14+'Dia 18'!C14+'Dia 19'!C14+'Dia 20'!C14+'Dia 21'!C14+'Dia 22'!C14+'Dia 23'!C14+'Dia 24'!C14+'Dia 25'!C14+'Dia 26'!C14+'Dia 27'!C14+'Dia 28'!C14+'Dia 29'!C14+'Dia 30'!C14+'Dia 31'!C14 -> 0 | D15: =+C15/$C$25 -> 0
B16: Pantry | C16: =+'Dia 1'!C15+'Dia 2'!C16+'Dia 3'!C16+'Dia 4'!C16+'Dia 5'!C16+'Dia 6'!C16+'Dia 7'!C16+'Dia 8'!C16+'Dia 9'!C16+'Dia 10'!C16+'Dia 11'!C16+'Dia 12'!C16+'Dia 13'!C16+'Dia 14'!C16+'Dia 15'!C16+'Dia 16'!C16+'Dia 17'!C16+'Dia 18'!C16+'Dia 19'!C16+'Dia 20'!C16+'Dia 21'!C16+'Dia 22'!C16+'Dia 23'!C16+'Dia 24'!C16+'Dia 25'!C16+'Dia 26'!C16+'Dia 27'!C16+'Dia 28'!C16+'Dia 29'!C16+'Dia 30'!C16+'Dia 31'!C16 -> 650 | D16: =+C16/$C$25 -> 0.001763507
B17: Comunicaciones | C17: =+'Dia 1'!C16+'Dia 2'!C17+'Dia 3'!C17+'Dia 4'!C17+'Dia 5'!C17+'Dia 6'!C17+'Dia 7'!C17+'Dia 8'!C17+'Dia 9'!C17+'Dia 10'!C17+'Dia 11'!C17+'Dia 12'!C17+'Dia 13'!C17+'Dia 14'!C17+'Dia 15'!C17+'Dia 16'!C17+'Dia 17'!C17+'Dia 18'!C17+'Dia 19'!C17+'Dia 20'!C17+'Dia 21'!C17+'Dia 22'!C17+'Dia 23'!C17+'Dia 24'!C17+'Dia 25'!C17+'Dia 26'!C17+'Dia 27'!C17+'Dia 28'!C17+'Dia 29'!C17+'Dia 30'!C17+'Dia 31'!C17 -> 67500 | D17: =+C17/$C$25 -> 0.18313342
B18: Publicidad | C18: =+'Dia 1'!C17+'Dia 2'!C18+'Dia 3'!C18+'Dia 4'!C18+'Dia 5'!C18+'Dia 6'!C18+'Dia 7'!C18+'Dia 8'!C18+'Dia 9'!C18+'Dia 10'!C18+'Dia 11'!C18+'Dia 12'!C18+'Dia 13'!C18+'Dia 14'!C18+'Dia 15'!C18+'Dia 16'!C18+'Dia 17'!C18+'Dia 18'!C18+'Dia 19'!C18+'Dia 20'!C18+'Dia 21'!C18+'Dia 22'!C18+'Dia 23'!C18+'Dia 24'!C18+'Dia 25'!C18+'Dia 26'!C18+'Dia 27'!C18+'Dia 28'!C18+'Dia 29'!C18+'Dia 30'!C18+'Dia 31'!C18 -> 24750 | D18: =+C18/$C$25 -> 0.06714892
B19: Insumos de Limpieza | C19: =+'Dia 1'!C18+'Dia 2'!C19+'Dia 3'!C19+'Dia 4'!C19+'Dia 5'!C19+'Dia 6'!C19+'Dia 7'!C19+'Dia 8'!C19+'Dia 9'!C19+'Dia 10'!C19+'Dia 11'!C19+'Dia 12'!C19+'Dia 13'!C19+'Dia 14'!C19+'Dia 15'!C19+'Dia 16'!C19+'Dia 17'!C19+'Dia 18'!C19+'Dia 19'!C19+'Dia 20'!C19+'Dia 21'!C19+'Dia 22'!C19+'Dia 23'!C19+'Dia 24'!C19+'Dia 25'!C19+'Dia 26'!C19+'Dia 27'!C19+'Dia 28'!C19+'Dia 29'!C19+'Dia 30'!C19+'Dia 31'!C19 -> 0 | D19: =+C19/$C$25 -> 0
B20: Mantenimiento | C20: =+'Dia 1'!C19+'Dia 2'!C20+'Dia 3'!C20+'Dia 4'!C20+'Dia 5'!C20+'Dia 6'!C20+'Dia 7'!C20+'Dia 8'!C20+'Dia 9'!C20+'Dia 10'!C20+'Dia 11'!C20+'Dia 12'!C20+'Dia 13'!C20+'Dia 14'!C20+'Dia 15'!C20+'Dia 16'!C20+'Dia 17'!C20+'Dia 18'!C20+'Dia 19'!C20+'Dia 20'!C20+'Dia 21'!C20+'Dia 22'!C20+'Dia 23'!C20+'Dia 24'!C20+'Dia 25'!C20+'Dia 26'!C20+'Dia 27'!C20+'Dia 28'!C20+'Dia 29'!C20+'Dia 30'!C20+'Dia 31'!C20 -> 7000 | D20: =+C20/$C$25 -> 0.018991614
B21: Insumos para la tienda | C21: =+'Dia 1'!C20+'Dia 2'!C21+'Dia 3'!C21+'Dia 4'!C21+'Dia 5'!C21+'Dia 6'!C21+'Dia 7'!C21+'Dia 8'!C21+'Dia 9'!C21+'Dia 10'!C21+'Dia 11'!C21+'Dia 12'!C21+'Dia 13'!C21+'Dia 14'!C21+'Dia 15'!C21+'Dia 16'!C21+'Dia 17'!C21+'Dia 18'!C21+'Dia 19'!C21+'Dia 20'!C21+'Dia 21'!C21+'Dia 22'!C21+'Dia 23'!C21+'Dia 24'!C21+'Dia 25'!C21+'Dia 26'!C21+'Dia 27'!C21+'Dia 28'!C21+'Dia 29'!C21+'Dia 30'!C21+'Dia 31'!C21 -> 0 | D21: =+C21/$C$25 -> 0
B22: Transporte | C22: =+'Dia 1'!C22+'Dia 2'!C22+'Dia 3'!C22+'Dia 4'!C22+'Dia 5'!C22+'Dia 6'!C22+'Dia 7'!C22+'Dia 8'!C22+'Dia 9'!C22+'Dia 10'!C22+'Dia 11'!C22+'Dia 12'!C22+'Dia 13'!C22+'Dia 14'!C22+'Dia 15'!C22+'Dia 16'!C22+'Dia 17'!C22+'Dia 18'!C22+'Dia 19'!C22+'Dia 20'!C22+'Dia 21'!C22+'Dia 22'!C22+'Dia 23'!C22+'Dia 24'!C22+'Dia 25'!C22+'Dia 26'!C22+'Dia 27'!C22+'Dia 28'!C22+'Dia 29'!C22+'Dia 30'!C22+'Dia 31'!C22 -> 0 | D22: =+C22/$C$25 -> 0
B23: Servicios contables | C23: =+'Dia 1'!C23+'Dia 2'!C23+'Dia 3'!C23+'Dia 4'!C23+'Dia 5'!C23+'Dia 6'!C23+'Dia 7'!C23+'Dia 8'!C23+'Dia 9'!C23+'Dia 10'!C23+'Dia 11'!C23+'Dia 12'!C23+'Dia 13'!C23+'Dia 14'!C23+'Dia 15'!C23+'Dia 16'!C23+'Dia 17'!C23+'Dia 18'!C23+'Dia 19'!C23+'Dia 20'!C23+'Dia 21'!C23+'Dia 22'!C23+'Dia 23'!C23+'Dia 24'!C23+'Dia 25'!C23+'Dia 26'!C23+'Dia 27'!C23+'Dia 28'!C23+'Dia 29'!C23+'Dia 30'!C23+'Dia 31'!C23 -> 0 | D23: =+C23/$C$25 -> 0
B24: Otros servicios comprados | C24: =+'Dia 1'!C23+'Dia 2'!C23+'Dia 3'!C23+'Dia 4'!C23+'Dia 5'!C23+'Dia 6'!C23+'Dia 7'!C23+'Dia 8'!C23+'Dia 9'!C23+'Dia 10'!C23+'Dia 11'!C23+'Dia 12'!C23+'Dia 13'!C23+'Dia 14'!C23+'Dia 15'!C23+'Dia 16'!C23+'Dia 17'!C23+'Dia 18'!C23+'Dia 19'!C23+'Dia 20'!C23+'Dia 21'!C23+'Dia 22'!C23+'Dia 23'!C23+'Dia 24'!C23+'Dia 25'!C23+'Dia 26'!C23+'Dia 27'!C23+'Dia 28'!C23+'Dia 29'!C23+'Dia 30'!C23+'Dia 31'!C23 -> 0 | D24: =+C24/$C$25 -> 0
B25: Total de Gastos | C25: =SUM(C11:C24) -> 368583.74
B26: Utilidad Bruta | C26: =+C9-C25 -> 3823088.2
B28: Impuestos
B29: 12,5% Seg.Social | C29: =+C11*0.125 -> 33585.467
B30: 5% Util. Fuerza de Trab. | C30: =+C11*0.05 -> 13434.187
B31: Total Impuestos | C31: =SUM(C29:C30) -> 47019.654
B32: Utilidad después de impuestos | C32: =+C26-C31 -> 3776068.6
B33: Impuesto sobre utilidades | C33: =+C32*0.35 -> 1321624
B34: Utilidad Neta | C34: =+C32-C33 -> 2454444.6
B36: Costo de la mercancía | C36: =+C13/C6 -> 0
B37: Costo por peso de Ingreso | C37: =+C25/C6 -> 0.07474544
